{
  "동물": [
    "고양이", "코끼리", "펭귄", "문어", "기린", "토끼", "사자", "돌고래", "독수리", "거북이",
    "강아지", "호랑이", "곰", "판다", "원숭이", "뱀", "악어", "하마", "코뿔소", "얼룩말",
    "낙타", "부엉이", "까마귀", "공작새", "플라밍고", "타조", "백조", "상어", "고래", "해파리",
    "불가사리", "오징어", "게", "나비", "무당벌레", "벌", "개미", "잠자리", "달팽이", "개구리",
    "카멜레온", "다람쥐", "고슴도치", "수달", "미어캣", "캥거루", "코알라", "사슴", "여우", "늑대"
  ],
  "음식": [
    "피자", "초밥", "햄버거", "떡볶이", "아이스크림", "치킨", "파스타", "김밥", "팬케이크", "타코",
    "라면", "만두", "비빔밥", "삼겹살", "불고기", "김치찌개", "냉면", "칼국수", "붕어빵", "팥빙수",
    "케이크", "도넛", "와플", "마카롱", "크로와상", "핫도그", "감자튀김", "샌드위치", "스테이크", "팝콘",
    "초콜릿", "사탕", "솜사탕", "젤리", "쿠키", "수박", "딸기", "바나나", "포도", "파인애플"
  ],
  "스포츠": [
    "축구", "야구", "농구", "수영", "태권도", "테니스", "스키", "볼링", "양궁", "서핑",
    "배구", "탁구", "배드민턴", "골프", "당구", "다이빙", "펜싱", "복싱", "유도", "레슬링",
    "피겨스케이팅", "아이스하키", "컬링", "스노보드", "체조", "역도", "마라톤", "허들", "높이뛰기", "장대높이뛰기",
    "원반던지기", "창던지기", "줄넘기", "줄다리기", "씨름", "트램펄린", "래프팅", "카누", "수구", "격투기"
  ],
  "직업": [
    "의사", "소방관", "요리사", "우주비행사", "경찰", "선생님", "화가", "조종사", "마술사", "탐정",
    "간호사", "치과의사", "수의사", "약사", "판사", "변호사", "과학자", "건축가", "사진작가", "발명가",
    "승무원", "잠수부", "군인", "스파이", "광대", "가수", "배우", "감독", "DJ", "발레리나",
    "지휘자", "아나운서", "기자", "농부", "목수", "이발사", "우편배달부", "대장장이", "도예가", "플로리스트"
  ],
  "탈것": [
    "자전거", "비행기", "잠수함", "로켓", "헬리콥터", "기차", "요트", "오토바이", "열기구", "스케이트보드",
    "자동차", "버스", "택시", "트럭", "소방차", "구급차", "경찰차", "탱크", "트랙터", "굴착기",
    "카누", "카약", "제트스키", "유람선", "뗏목", "돛단배", "곤돌라", "호버크래프트", "마차", "썰매",
    "케이블카", "모노레일", "지하철", "롤러코스터", "스쿠터", "세그웨이", "인력거", "스키리프트", "쇄빙선", "봅슬레이"
  ],
  "장소": [
    "학교", "병원", "해변", "놀이공원", "도서관", "공항", "동물원", "영화관", "캠핑장", "수족관",
    "등대", "사막", "정글", "동굴", "폭포", "온천", "빙하", "화산", "절벽", "섬",
    "성", "궁전", "피라미드", "교회", "사원", "감옥", "묘지", "콜로세움", "풍차", "전망대",
    "놀이터", "체육관", "볼링장", "스키장", "경기장", "아이스링크", "워터파크", "서커스", "수영장", "운동장",
    "슈퍼마켓", "빵집", "꽃집", "미용실", "주유소", "우체국", "식당", "카페", "은행", "소방서"
  ],
  "악기": [
    "피아노", "기타", "드럼", "바이올린", "트럼펫", "플루트", "하프", "첼로", "탬버린", "색소폰",
    "우쿨렐레", "하모니카", "아코디언", "오카리나", "리코더", "백파이프", "클라리넷", "오보에", "튜바", "트롬본",
    "심벌즈", "실로폰", "마라카스", "캐스터네츠", "봉고", "콩가", "반조", "만돌린", "팬플루트", "호른",
    "가야금", "거문고", "대금", "해금", "장구", "꽹과리", "징", "소고", "피리", "태평소"
  ],
  "날씨·자연": [
    "번개", "눈사람", "무지개", "태풍", "안개", "우박", "오로라", "토네이도", "소나기", "서리",
    "태양", "달", "별", "지구", "토성", "혜성", "은하수", "일식", "월식", "별똥별",
    "산", "강", "바다", "호수", "빙산", "사막", "협곡", "간헐천", "파도", "쓰나미",
    "장미", "튤립", "벚꽃", "민들레", "연꽃", "해바라기", "소나무", "야자수", "대나무", "버섯"
  ],
  "캐릭터": [
    "산타클로스", "해적", "공주", "로봇", "닌자", "마녀", "슈퍼히어로", "좀비", "요정", "드래곤",
    "왕", "기사", "카우보이", "인어공주", "뱀파이어", "늑대인간", "미이라", "유령", "외계인", "천사",
    "악마", "거인", "난쟁이", "유니콘", "피닉스", "고블린", "엘프", "광대", "해골", "프랑켄슈타인",
    "설인", "도깨비", "선녀", "손오공", "저팔계", "피터팬", "켄타우로스", "미노타우로스", "인어", "피에로"
  ],
  "사물": [
    "우산", "가위", "시계", "안경", "전화기", "풍선", "양초", "열쇠", "카메라", "나침반",
    "망치", "드라이버", "톱", "삽", "도끼", "빗자루", "사다리", "양동이", "돋보기", "손전등",
    "텔레비전", "냉장고", "세탁기", "선풍기", "다리미", "청소기", "전자레인지", "에어컨", "토스터", "믹서기",
    "컵", "접시", "냄비", "프라이팬", "젓가락", "숟가락", "포크", "도마", "주전자", "와인잔"
  ],
  "의류·패션": [
    "모자", "넥타이", "장갑", "목도리", "양말", "구두", "운동화", "슬리퍼", "부츠", "샌들",
    "선글라스", "귀걸이", "목걸이", "반지", "팔찌", "왕관", "투구", "가면", "망토", "앞치마",
    "한복", "기모노", "턱시도", "웨딩드레스", "청바지", "코트", "우비", "치마", "스카프", "베레모"
  ],
  "건물·구조물": [
    "집", "아파트", "오두막", "이글루", "텐트", "트리하우스", "등대", "풍차", "탑", "다리",
    "성", "궁전", "피라미드", "에펠탑", "자유의여신상", "빅벤", "콜로세움", "타지마할", "스핑크스", "만리장성",
    "댐", "터널", "관람차", "롤러코스터", "분수대", "우물", "굴뚝", "전망대", "천문대", "지하벙커"
  ]
}
